sax_ts.cp39-win32.pyd
sax_ts-1.2.dist-info/licenses/LICENSE
sax_ts-1.2.dist-info/METADATA
sax_ts-1.2.dist-info/WHEEL
sax_ts-1.2.dist-info/top_level.txt
sax_ts-1.2.dist-info/RECORD
