Metadata-Version: 2.4
Name: sax_ts
Version: 1.2
Summary: Symbolic Aggregate approXimation (SAX)
Author-email: "Stijn J. Rotman" <s.j.rotman@uvt.nl>
License-Expression: MIT
Requires-Python: >=3.9
License-File: LICENSE
Provides-Extra: test
Requires-Dist: pytest; extra == "test"
Requires-Dist: numpy; extra == "test"
Dynamic: license-file
